Metadata-Version: 2.1
Name: mvc-snake-game
Version: 1.1.8
Summary: MVC Snake game
Author: AbsoluteZero
Author-email: kasperekd7@yandex.ru
